contextualise_ssh_server/__init__.py
contextualise_ssh_server/cli.py
contextualise_ssh_server/config.py
contextualise_ssh_server/contextualise_ssh_server.conf
contextualise_ssh_server/disable-pam-ssh.sh
contextualise_ssh_server/enable-pam-ssh.sh
contextualise_ssh_server/feudal_adapter.conf
contextualise_ssh_server/feudal_adapter.template.conf
contextualise_ssh_server/logsetup.py
contextualise_ssh_server/motley_cue.conf
contextualise_ssh_server/motley_cue.template.conf
contextualise_ssh_server/parse_args.py
contextualise_ssh_server-0.8.6.dist-info/LICENSE
contextualise_ssh_server-0.8.6.dist-info/METADATA
contextualise_ssh_server-0.8.6.dist-info/WHEEL
contextualise_ssh_server-0.8.6.dist-info/entry_points.txt
contextualise_ssh_server-0.8.6.dist-info/pbr.json
contextualise_ssh_server-0.8.6.dist-info/top_level.txt
contextualise_ssh_server-0.8.6.dist-info/RECORD
