Metadata-Version: 2.1
Name: contextualise-ssh-server
Version: 0.8.6
Summary: Contextualise motley-cue and pam-ssh-oidc on a VM Server
Home-page: https://github.com/marcvs/contextualise_ssh_server
Author: Marcus Hardt
Author-email: hardt@kit.edu
License: MIT license
Project-URL: Bug Tracker, https://github.com/marcvs/contextualise_ssh_server/issues
Classifier: Programming Language :: Python :: 3
License-File: LICENSE
Requires-Dist: configparser
Requires-Dist: flaat
Requires-Dist: jinja2
